[
null,
{"id":1,"expanded":false,"name":"Choosing-Terminal","order":1,"parentId":0,"scrollX":929.1428571428571,"scrollY":522.8571428571428},
{"id":2,"expanded":false,"name":"Empty Field","order":2,"parentId":1,"scrollX":1281.6,"scrollY":1852.8},
{"id":3,"expanded":false,"name":"Block Room","order":3,"parentId":1,"scrollX":1300.8,"scrollY":732},
{"id":4,"expanded":false,"name":"VoidPath","order":4,"parentId":1,"scrollX":1281.6,"scrollY":1485.6},
{"id":5,"expanded":false,"name":"Incipite Forest","order":5,"parentId":1,"scrollX":2048,"scrollY":624},
{"id":6,"expanded":false,"name":"Grand Waterways","order":6,"parentId":1,"scrollX":886.5,"scrollY":2602.5},
{"id":7,"expanded":false,"name":"The Other Forest","order":7,"parentId":1,"scrollX":1626,"scrollY":915},
{"id":8,"expanded":true,"name":"Urdina","order":10,"parentId":1,"scrollX":1182.5454545454545,"scrollY":665.4545454545455},
{"id":9,"expanded":false,"name":"Spooky Forest","order":8,"parentId":1,"scrollX":1626,"scrollY":915},
{"id":10,"expanded":false,"name":"Cave","order":9,"parentId":1,"scrollX":1330.6666666666667,"scrollY":856},
{"id":11,"expanded":true,"name":"The Great Cliffs","order":12,"parentId":8,"scrollX":1965.818181818182,"scrollY":5048.727272727273},
{"id":12,"expanded":false,"name":"Room","order":11,"parentId":8,"scrollX":1182.5454545454545,"scrollY":665.4545454545455},
{"id":13,"expanded":true,"name":"Mysterious Desert","order":14,"parentId":8,"scrollX":1165.0909090909092,"scrollY":2934.5454545454545},
{"id":14,"expanded":false,"name":"The Mansion","order":42,"parentId":41,"scrollX":2148,"scrollY":6306.666666666667},
{"id":15,"expanded":false,"name":"Temple","order":13,"parentId":11,"scrollX":1165.0909090909092,"scrollY":774.5454545454546},
{"id":16,"expanded":false,"name":"BrokenIslands","order":15,"parentId":1,"scrollX":1234.909090909091,"scrollY":3901.0909090909095},
{"id":17,"expanded":true,"name":"Hedge Maze","order":24,"parentId":1,"scrollX":2890.6666666666665,"scrollY":1626.6666666666667},
{"id":18,"expanded":false,"name":"House","order":25,"parentId":17,"scrollX":650.4,"scrollY":366},
{"id":19,"expanded":true,"name":"Raising","order":26,"parentId":1,"scrollX":2890.6666666666665,"scrollY":1626.6666666666667},
{"id":20,"expanded":true,"name":"Sky","order":18,"parentId":1,"scrollX":7162.909090909091,"scrollY":6922.909090909091},
{"id":21,"expanded":false,"name":"Ice Chamber","order":19,"parentId":20,"scrollX":1620,"scrollY":898.5},
{"id":22,"expanded":false,"name":"Quiz Room","order":20,"parentId":20,"scrollX":722.6666666666666,"scrollY":406.6666666666667},
{"id":23,"expanded":false,"name":"Desert Underground","order":21,"parentId":20,"scrollX":2050.4,"scrollY":834.4},
{"id":24,"expanded":false,"name":"Corrupted Wastes","order":40,"parentId":0,"scrollX":1626,"scrollY":915},
{"id":25,"expanded":false,"name":"Sky Temple f1","order":22,"parentId":20,"scrollX":2648,"scrollY":1926.6666666666667},
{"id":26,"expanded":false,"name":"Sky Temple f2","order":23,"parentId":25,"scrollX":2994,"scrollY":1926},
{"id":27,"expanded":false,"name":"Dead Lands","order":27,"parentId":1,"scrollX":2184,"scrollY":3092},
{"id":28,"expanded":true,"name":"Nightmare Realm l1","order":28,"parentId":1,"scrollX":2848,"scrollY":2304},
{"id":29,"expanded":true,"name":"Nightmare Realm l2","order":29,"parentId":28,"scrollX":2048,"scrollY":2240},
{"id":30,"expanded":true,"name":"Nightmare Realm l3","order":30,"parentId":29,"scrollX":1013.3333333333334,"scrollY":1224},
{"id":31,"expanded":false,"name":"BonusArea","order":31,"parentId":30,"scrollX":722.6666666666666,"scrollY":406.6666666666667},
{"id":32,"expanded":true,"name":"Transition","order":32,"parentId":1,"scrollX":2890.6666666666665,"scrollY":1626.6666666666667},
{"id":33,"expanded":false,"name":"Transition (Glitch)","order":33,"parentId":32,"scrollX":3716,"scrollY":594},
{"id":34,"expanded":false,"name":"House B1","order":35,"parentId":35,"scrollX":832,"scrollY":640},
{"id":35,"expanded":true,"name":"HouseOutside","order":34,"parentId":32,"scrollX":1695.6,"scrollY":456},
{"id":36,"expanded":true,"name":"The Infinite Field","order":16,"parentId":1,"scrollX":4333.090909090909,"scrollY":2323.6363636363635},
{"id":37,"expanded":false,"name":"House F1","order":36,"parentId":35,"scrollX":712,"scrollY":640},
{"id":38,"expanded":false,"name":"House F2","order":37,"parentId":35,"scrollX":832,"scrollY":640},
{"id":39,"expanded":false,"name":"Shed","order":38,"parentId":35,"scrollX":650.4,"scrollY":366},
{"id":40,"expanded":false,"name":"IceLobby","order":39,"parentId":0,"scrollX":712,"scrollY":914.6666666666666},
{"id":41,"expanded":true,"name":"IcyMaze","order":41,"parentId":0,"scrollX":712,"scrollY":2545.3333333333335},
{"id":42,"expanded":true,"name":"Tundra","order":43,"parentId":0,"scrollX":2148,"scrollY":3429.3333333333335},
{"id":43,"expanded":false,"name":"Waterfall","order":44,"parentId":0,"scrollX":1626,"scrollY":915},
{"id":44,"expanded":false,"name":"Underwater Caves","order":45,"parentId":0,"scrollX":2168,"scrollY":1626.6666666666667},
{"id":45,"expanded":false,"name":"Icy City","order":46,"parentId":0,"scrollX":770.6666666666666,"scrollY":644},
{"id":46,"expanded":false,"name":"Hidden Caves","order":47,"parentId":0,"scrollX":712,"scrollY":564},
{"id":47,"expanded":false,"name":"Thawing Path","order":48,"parentId":0,"scrollX":722.6666666666666,"scrollY":406.6666666666667},
{"id":48,"expanded":true,"name":"Temple Entrance","order":49,"parentId":0,"scrollX":722.6666666666666,"scrollY":406.6666666666667},
{"id":49,"expanded":false,"name":"Shack","order":17,"parentId":36,"scrollX":1182.5454545454545,"scrollY":665.4545454545455},
{"id":50,"expanded":true,"name":"Ice Temple F1","order":50,"parentId":48,"scrollX":1602.6666666666667,"scrollY":914.6666666666666},
{"id":51,"expanded":false,"name":"Ice Temple F2","order":51,"parentId":50,"scrollX":722.6666666666666,"scrollY":406.6666666666667}
]